ose_app/AppModule.py
ose_app/OntologyDataStore.py
ose_app/PermissionManager.py
ose_app/SpreadsheetSearcher.py
ose_app/__init__.py
ose_app/app.py
ose_app/constants.py
ose_app/custom_json.py
ose_app/default_config.py
ose_app/gh.py
ose_app/guards/__init__.py
ose_app/guards/verify_login.py
ose_app/guards/with_permission.py
ose_app/jinja_extensions/__init__.py
ose_app/routes/__init__.py
ose_app/routes/admin.py
ose_app/routes/auth.py
ose_app/routes/edit.py
ose_app/routes/main.py
ose_app/routes/search.py
ose_app/routes/status.py
ose_app/routes/visualize.py
ose_app/routes/api/__init__.py
ose_app/routes/api/edit.py
ose_app/routes/api/external.py
ose_app/routes/api/plugins.py
ose_app/routes/api/release.py
ose_app/routes/api/repos.py
ose_app/routes/api/scripts.py
ose_app/routes/api/search.py
ose_app/routes/api/settings.py
ose_app/routes/api/validate.py
ose_app/routes/api/visualise.py
ose_app/static/addicto.release.json
ose_app/static/bcio.release.json
ose_app/static/example.json
ose_app/static/excel-bootstrap-table-filter-bundle.js
ose_app/static/excel-bootstrap-table-filter-bundle.min.js
ose_app/static/excel-bootstrap-table-filter-style.css
ose_app/static/gmho.release.json
ose_app/static/main.css
ose_app/static/main.scss
ose_app/static/mindmup-editabletable.js
ose_app/static/test.dot
ose_app/static/js/admin.js
ose_app/static/js/editor.js
ose_app/static/js/release.js
ose_app/static/js/settings.js
ose_app/static/js/visualise.js
ose_app/static/js/assets/CollapsibleCard.css
ose_app/static/js/assets/editor.css
ose_app/static/js/assets/release.css
ose_app/static/js/assets/settings.css
ose_app/static/js/assets/visualise.css
ose_app/static/js/chunks/BToastOrchestrator.vue_vue_type_style_index_0_lang-CgGO-ddH-BDr_frBe.js
ose_app/static/js/chunks/CollapsibleCard-DoX0kPCZ.js
ose_app/static/js/chunks/Diagnostic.vue_vue_type_script_setup_true_lang-CBzsmnqW.js
ose_app/static/js/chunks/_plugin-vue_export-helper-DlAUqK2U.js
ose_app/static/js/chunks/bootbox-D3SJ_Fwv.js
ose_app-0.3.0.dist-info/METADATA
ose_app-0.3.0.dist-info/WHEEL
ose_app-0.3.0.dist-info/top_level.txt
ose_app-0.3.0.dist-info/RECORD
