Metadata-Version: 2.4
Name: ose-app
Version: 0.3.0
Summary: Flask web application for OntoSpreadEd - Ontology spreadsheet editor
Requires-Python: >=3.12
Requires-Dist: ose-core==0.3.0
Requires-Dist: Flask==2.3.3
Requires-Dist: Flask-SQLAlchemy==3.1.1
Requires-Dist: Flask-Injector
Requires-Dist: GitHub-Flask
Requires-Dist: flask-cors==3.0.10
Requires-Dist: flask-executor
Requires-Dist: Flask-Migrate
Provides-Extra: cli
Requires-Dist: ose-cli; extra == "cli"
Provides-Extra: dev
Requires-Dist: pytest; extra == "dev"
Requires-Dist: ruff; extra == "dev"
Provides-Extra: all
Requires-Dist: ose-cli; extra == "all"
Requires-Dist: ose-plugin-addicto; extra == "all"
Requires-Dist: ose-plugin-bcio; extra == "all"
Requires-Dist: ose-plugin-hierarchical-spreadsheets; extra == "all"
Provides-Extra: plugins
Requires-Dist: ose-plugin-addicto; extra == "plugins"
Requires-Dist: ose-plugin-bcio; extra == "plugins"
Requires-Dist: ose-plugin-hierarchical-spreadsheets; extra == "plugins"
